regfile.v
module regfile(
    input clk,
    input write_enable,
    input [4:0] read_address1, read_address2, write_address3,
    input [31:0] write_data3,
    output [31:0] read_data1, read_data2
    );
    
reg [31:0] rf[31:0];

always @ (posedge clk)
    if (write_enable)  rf[write_address3] <= write_data3;
  
assign read_data1 = (read_address1 != 0) ? rf[read_address1] : 0;    
assign read_data2 = (read_address2 != 0) ? rf[read_address2] : 0;    
    
endmodule

regfile_test.v
`include "regfile.v"

module testbench();

  reg clk;
  reg reg_write;

  reg [4:0]  read_register1,read_register2,write_register;
  reg [31:0] write_data;
  wire [31:0] read_data1, read_data2;

  regfile testreg(clk, reg_write, read_register1, read_register2, write_register, write_data, read_data1, read_data2);

  initial
    begin
      $dumpfile("regfile_test.vcd");
      $dumpvars(0, testreg);

      $monitor("%h, %h, %h, %h", testreg.rf[1], testreg.rf[2], testreg.read_data1, testreg.read_data2);

      $display("rf[1]       rf[2]       read_data1        read_data2");

      read_register1 <= 1; read_register2 <= 2; write_register <= 1; write_data  <= 5; 

      reg_write <= 1; #10;
      reg_write <= 0; #10;

      read_register1 <= 1; read_register2 <= 2; write_register <= 2; write_data  <= 6;

      reg_write <= 1; #10;
      reg_write <= 0; #10;

      read_register1 <= 1; read_register2 <= 2; write_register <= 1; write_data  <= 8;

      reg_write <= 1; #10;
      reg_write <= 0; #10;

      // 0 register
      read_register1 <=  0; read_register2 <= 2; write_register <= 0; write_data  <= 8;

      reg_write <= 1; #10;
      reg_write <= 0; #10;

      #200;
      $finish;
    end

  // generate clock
  always
    begin
      clk <= 1; # 5; clk <= 0; # 5;
    end

endmodule

regfile_test.vcd
$date
	Wed Aug 21 09:18:52 2019
$end
$version
	Icarus Verilog
$end
$timescale
	1s
$end
$scope module testbench $end
$scope module testreg $end
$var wire 1 ! clk $end
$var wire 5 " read_address1 [4:0] $end
$var wire 5 # read_address2 [4:0] $end
$var wire 5 $ write_address3 [4:0] $end
$var wire 32 % write_data3 [31:0] $end
$var wire 1 & write_enable $end
$var wire 32 ' read_data2 [31:0] $end
$var wire 32 ( read_data1 [31:0] $end
$upscope $end
$upscope $end
$enddefinitions $end
#0
$dumpvars
b101 (
bx '
1&
b101 %
b1 $
b10 #
b1 "
1!
$end
#5
0!
#10
1!
0&
#15
0!
#20
b110 '
1!
1&
b110 %
b10 $
#25
0!
#30
1!
0&
#35
0!
#40
b1000 (
1!
1&
b1000 %
b1 $
#45
0!
#50
1!
0&
#55
0!
#60
b0 (
1!
1&
b0 $
b0 "
#65
0!
#70
1!
0&
